[
  {
    "id": 1,
    "name": "ষষ্ঠ",
    "male": "১",
    "female": "১",
    "total": "২"
  },
  {
    "id": 2,
    "name": "সপ্তম",
    "male": "২",
    "female": "০",
    "total": "২"
  },
  {
    "id": 3,
    "name": "অষ্টম",
    "male": "১",
    "female": "১",
    "total": "২"
  },
  {
    "id": 4,
    "name": "নবম",
    "department": "বিজ্ঞান, মানবিক, ব্যবসায় শিক্ষা",
    "male": ["০", "২", "৫"],
    "female": ["১", "০", "১"],
    "total": ["১", "২", "৬"]
  },
  {
    "id": 5,
    "name": "দশম",
    "department": "বিজ্ঞান, মানবিক, ব্যবসায় শিক্ষা",
    "male": ["২", "০", "০"],
    "female": ["১", "০", "০"],
    "total": ["৩", "০", "০"]
  }
]
